model_calling/__init__.py
model_calling/__main__.py
model_calling/adapter.py
model_calling/cache.py
model_calling/callbacks.py
model_calling/capability_cache.py
model_calling/capability_testing.py
model_calling/client.py
model_calling/config.py
model_calling/embedding_adapter.py
model_calling/granite_guardian_adapter.py
model_calling/ollama_adapter.py
model_calling/ollama_embedding_adapter.py
model_calling/registry.py
model_calling/server.py
model_calling/thinking.py
model_calling/vllm_adapter.py
model_calling/hosted/__init__.py
model_calling/hosted/anthropic_adapter.py
model_calling/hosted/cohere_adapter.py
model_calling/hosted/cohere_embedding_adapter.py
model_calling/hosted/openai_adapter.py
model_calling/hosted/openai_embedding_adapter.py
model_calling-0.1.0.dist-info/licenses/LICENSE
model_calling-0.1.0.dist-info/METADATA
model_calling-0.1.0.dist-info/WHEEL
model_calling-0.1.0.dist-info/entry_points.txt
model_calling-0.1.0.dist-info/top_level.txt
model_calling-0.1.0.dist-info/RECORD
